README.md
setup.py
sql_sanitizer/__init__.py
sql_sanitizer.egg-info/PKG-INFO
sql_sanitizer.egg-info/SOURCES.txt
sql_sanitizer.egg-info/dependency_links.txt
sql_sanitizer.egg-info/not-zip-safe
sql_sanitizer.egg-info/top_level.txt