Metadata-Version: 1.0
Name: sql-sanitizer
Version: 0.3
Summary: Utility to check if the given input is sanitized for sql injection
Home-page: http://github.com/worldofprasanna/sql_sanitizer
Author: Prasanna V
Author-email: prasannacse2005@gmail.com
License: MIT
Platform: UNKNOWN
